classno/__init__.py
classno/_casting.py
classno/_delattrs.py
classno/_dunders.py
classno/_feature_handlers.py
classno/_fields.py
classno/_getattrs.py
classno/_hooks.py
classno/_setattrs.py
classno/_validation.py
classno/constants.py
classno/core.py
classno/exceptions.py
classno-0.0.8.dist-info/LICENSE
classno-0.0.8.dist-info/METADATA
classno-0.0.8.dist-info/WHEEL
classno-0.0.8.dist-info/RECORD
